<annotation verified="yes">
	<folder>train</folder>
	<filename>CCTV_Dori_Ran_Ruff_2023_08_16_133624.png</filename>
	<path>C:\Users\Jose.Espinosa\Documents\Axity\Axity_Trainer\research\object_detection\images\train\CCTV_Dori_Ran_Ruff_2023_08_16_133624.png</path>
	<source>
		<database>Unknown</database>
	</source>
	<size>
		<width>2048</width>
		<height>1536</height>
		<depth>3</depth>
	</size>
	<segmented>0</segmented>
	<object>
		<name>RufflesQ_48_F</name>
		<pose>Unspecified</pose>
		<truncated>0</truncated>
		<difficult>0</difficult>
		<bndbox>
			<xmin>94</xmin>
			<ymin>1049</ymin>
			<xmax>618</xmax>
			<ymax>1463</ymax>
		</bndbox>
	</object>
	<object>
		<name>DoritosN_61_F</name>
		<pose>Unspecified</pose>
		<truncated>0</truncated>
		<difficult>0</difficult>
		<bndbox>
			<xmin>149</xmin>
			<ymin>782</ymin>
			<xmax>655</xmax>
			<ymax>1129</ymax>
		</bndbox>
	</object>
	<object>
		<name>Rancheritos_58_F</name>
		<pose>Unspecified</pose>
		<truncated>0</truncated>
		<difficult>0</difficult>
		<bndbox>
			<xmin>188</xmin>
			<ymin>527</ymin>
			<xmax>669</xmax>
			<ymax>845</ymax>
		</bndbox>
	</object>
</annotation>
